pysobol/__init__.py
pysobol/__main__.py
pysobol/data.py
pysobol-0.0.1.dist-info/METADATA
pysobol-0.0.1.dist-info/WHEEL
pysobol-0.0.1.dist-info/top_level.txt
pysobol-0.0.1.dist-info/RECORD
