Metadata-Version: 2.1
Name: pysobol
Version: 0.0.1
Summary: Efficient Sobol sequence generator with NumPy
Home-page: https://github.com/archibate/pysobol
Author: archibate
Author-email: 1931127624@qq.com
License: MIT
Keywords: graphics,renderer
Platform: UNKNOWN
Classifier: Intended Audience :: Developers
Classifier: Intended Audience :: Science/Research
Classifier: Topic :: Multimedia :: Graphics
Classifier: Topic :: Games/Entertainment :: Simulation
Classifier: Operating System :: OS Independent
Requires-Python: >=3.6
Requires-Dist: numpy
